{
  "greeting": "Hello Bastard",
  "name": "Izzah of the Azamest",
  "greetingText": "22 sounding real serious all of a sudden (taylor baaji aap kahan hain)",
  "wishText": "may you get your favourite sabun to eat this special day",
  "imagePath": "img/izzah2.png",
  "text1": "JANAM DIN MUBARIK:D",
  "textInChatBox": "happy birthday haha london british botow o watah...",
  "sendButtonLabel": "Bhej",
  "text2": "wait",
  "text3": "that's SO outdated who tf does that",
  "text4": "hence i wanted to do something",
  "text4Adjective": "special",
  "text5Entry": "because",
  "text5Content": "u are special",
  "smiley": ":3",
  "bigTextPart1": "S",
  "bigTextPart2": "O",
  "wishHeading": "cake murder 20 oct",
  "outroText": "I hope you'll have a great 2 birthdays (hehe). I love you.",
  "replayText": "Click here, if you want to watch it again.",
  "outroSmiley": ":3"
}
